django_cleanhtmlfield/__init__.py
django_cleanhtmlfield/fields.py
django_cleanhtmlfield/helpers.py
django_cleanhtmlfield-1.4.0.dist-info/licenses/LICENSE
tests/__init__.py
tests/manage.py
tests/cleanhtmlfield_testapp/__init__.py
tests/cleanhtmlfield_testapp/settings.py
tests/cleanhtmlfield_testapp/test_clean_html.py
tests/cleanhtmlfield_testapp/tests_clean_styles.py
tests/cleanhtmlfield_testapp/urls.py
tests/myapp/__init__.py
tests/myapp/models.py
tests/myapp/tests.py
tests/myapp/migrations/0001_initial.py
tests/myapp/migrations/__init__.py
django_cleanhtmlfield-1.4.0.dist-info/METADATA
django_cleanhtmlfield-1.4.0.dist-info/WHEEL
django_cleanhtmlfield-1.4.0.dist-info/top_level.txt
django_cleanhtmlfield-1.4.0.dist-info/RECORD
